edatest/__init__.py
edatest/edatest.py
edatest-0.0.4.dist-info/LICENSE
edatest-0.0.4.dist-info/METADATA
edatest-0.0.4.dist-info/WHEEL
edatest-0.0.4.dist-info/top_level.txt
edatest-0.0.4.dist-info/RECORD
