Metadata-Version: 2.1
Name: edatest
Version: 0.0.4
Summary: This is a simple package used to run Edabit tests.
Home-page: https://gitlab.com/nicholas.walk/edatest
Author: Nicholas Walker
Author-email: nicholas.walk@gmail.com
License: UNKNOWN
Platform: UNKNOWN
Classifier: Programming Language :: Python :: 3
Classifier: License :: OSI Approved :: MIT License
Classifier: Operating System :: OS Independent
Requires-Python: >=3.6
